bulma_sphinx_theme/__init__.py
bulma_sphinx_theme/assets/scripts/bulma-sphinx-theme.js
bulma_sphinx_theme/assets/scripts/gumshoe-patched.js
bulma_sphinx_theme/assets/styles/abstracts/_mixins.scss
bulma_sphinx_theme/assets/styles/base/_icons.scss
bulma_sphinx_theme/assets/styles/base/_index.sass
bulma_sphinx_theme/assets/styles/base/_typography.scss
bulma_sphinx_theme/assets/styles/bulma-sphinx-theme.sass
bulma_sphinx_theme/assets/styles/components/_article-bottom.scss
bulma_sphinx_theme/assets/styles/components/_article-top.scss
bulma_sphinx_theme/assets/styles/components/_back-to-top.scss
bulma_sphinx_theme/assets/styles/components/_brand.scss
bulma_sphinx_theme/assets/styles/components/_breadcrumbs.scss
bulma_sphinx_theme/assets/styles/components/_edit-page.scss
bulma_sphinx_theme/assets/styles/components/_index.sass
bulma_sphinx_theme/assets/styles/components/_last-updated.scss
bulma_sphinx_theme/assets/styles/components/_prev-next.scss
bulma_sphinx_theme/assets/styles/components/_search-button.scss
bulma_sphinx_theme/assets/styles/components/_search-field.sass
bulma_sphinx_theme/assets/styles/components/_search-icon.scss
bulma_sphinx_theme/assets/styles/components/_search-results.scss
bulma_sphinx_theme/assets/styles/components/_search-wrapper.scss
bulma_sphinx_theme/assets/styles/components/_search.sass
bulma_sphinx_theme/assets/styles/components/_sidenav-brand.scss
bulma_sphinx_theme/assets/styles/components/_sidenav-panel.scss
bulma_sphinx_theme/assets/styles/components/_switcher-theme.scss
bulma_sphinx_theme/assets/styles/content/_admonitions.scss
bulma_sphinx_theme/assets/styles/content/_api.scss
bulma_sphinx_theme/assets/styles/content/_blocks.sass
bulma_sphinx_theme/assets/styles/content/_code.scss
bulma_sphinx_theme/assets/styles/content/_footnotes.sass
bulma_sphinx_theme/assets/styles/content/_gui-labels.scss
bulma_sphinx_theme/assets/styles/content/_images.sass
bulma_sphinx_theme/assets/styles/content/_index.sass
bulma_sphinx_theme-0.2.1.dist-info/LICENSE
bulma_sphinx_theme-0.2.1.dist-info/METADATA
bulma_sphinx_theme-0.2.1.dist-info/WHEEL
bulma_sphinx_theme-0.2.1.dist-info/entry_points.txt
bulma_sphinx_theme-0.2.1.dist-info/RECORD